{
  "options": [
    "wpbulky_params_setting",
    "vi_wpbulky_full_screen_option",
    "*_dismiss_notices",
    "*_wp_reviewed",
    "*_start_use",
    "villatheme_hide_admin_toolbar",
    "villatheme_hide_notices_*"
  ],
  "transients": [
    "villatheme_call",
    "*_hide_notices",
    "villatheme_hide_notices_*",
    "villatheme_notices",
    "villatheme_called",
    "villatheme_ads"
  ],
  "cron_jobs": [
    "vi_wpbulky_remove_revision"
  ],
  "custom_tables": [],
  "metadata": [
    "_wp_attachment_image_alt"
  ],
  "has_uninstall": false,
  "last_checked": "2026-02-24T22:56:09.738Z"
}