{
  "options": [
    "wpas_setup",
    "wpas_plugin_setup",
    "wpas_skip_wizard_setup",
    "wpas_options",
    "wpas_dismiss_free_addon_page",
    "wpas_version",
    "active_sitewide_plugins",
    "rdn_fetch_*",
    "wpas_htaccess_deny_all_fixed",
    "wpas_original_files",
    "wpas_default_channels_added",
    "wpas_default_ticket_types_added",
    "*_options",
    "wpas_db_version",
    "wpas_setup_email_templates",
    "wisdom_example_options_settings",
    "wisdom_deactivation_reason_*",
    "wisdom_deactivation_details_*",
    "wisdom_last_track_time",
    "wisdom_allow_tracking",
    "wisdom_notification_times",
    "wisdom_block_notice",
    "wisdom_collect_email",
    "wisdom_admin_emails",
    "sm_session_db_version"
  ],
  "transients": [
    "wpas_tickets_counts",
    "wpas_addonsx",
    "wpas_product_term_*",
    "rn_last_notification_*",
    "wpas_wp_users_count",
    "update_plugins",
    "wpas_activity_meta_post_*"
  ],
  "cron_jobs": [
    "attachments_dir_cleanup_action",
    "wpas_tickets_cleanup_action",
    "put_do_weekly_action",
    "wp_session_database_gc"
  ],
  "custom_tables": [],
  "metadata": [
    "_wpas_is_waiting_client_reply",
    "wpas_reply_was_deleted",
    "_wpas_status",
    "wpas_close_ticket_prevent_client_notification",
    "_wpas_is_ticket_template",
    "_ticket_closed_on",
    "_ticket_closed_on_gmt",
    "_wpas_assignee",
    "_wpas_last_reply_date",
    "_wpas_last_reply_date_gmt",
    "_wpas_product_term",
    "_wpas_ttl_calculated_time_spent_on_ticket",
    "_wpas_ttl_adjustments_to_time_spent_on_ticket",
    "_wpas_final_time_spent_on_ticket",
    "color",
    "_wpas_secondary_assignee",
    "_wpas_tertiary_assignee",
    "auto_delete_attachments",
    "auto_delete_attachments_type",
    "_wp_attachment_metadata",
    "_wpas_*",
    "wpas_reply_was_edited",
    "_wpas_ttl_replies_by_customer",
    "_wpas_ttl_replies_by_agent",
    "_wpas_ttl_replies",
    "_wpas_first_addl_interested_party_name",
    "_wpas_first_addl_interested_party_email",
    "_wpas_second_addl_interested_party_name",
    "_wpas_second_addl_interested_party_email",
    "_wpas_pbtk_flag",
    "is_anonymize"
  ],
  "has_uninstall": true,
  "last_checked": "2026-02-24T22:39:46.567Z"
}