{
  "options": [
    "ta_request_check_excluded_routes",
    "ta_publishable_key",
    "ta_secret_key",
    "ta_request_check_enabled",
    "ta_user_verification_enabled",
    "ta_button_default_text",
    "ta_button_default_style",
    "ta_button_show_info",
    "ta_button_default_width",
    "ta_restricted_user_verification_page",
    "ta_traffic_validation_enabled",
    "ta_user_validation_enabled",
    "ta_user_validation_auto_bind",
    "ta_user_validation_bind_existing",
    "ta_user_validation_identifier_type",
    "ta_request_check_timeout_ms"
  ],
  "transients": [],
  "cron_jobs": [],
  "custom_tables": [],
  "metadata": [
    "restricted_ta",
    "ta_restricted_reason",
    "ta_needs_verification",
    "ta_verification_reason",
    "verified_ta",
    "login_with_ta",
    "show_admin_bar_front",
    "blocked_ta",
    "ta_verification_level",
    "ta_email_validation_valid",
    "ta_unique_browser_fingerprint",
    "ta_pending_session_binding",
    "ta_bound",
    "ta_bound_date",
    "ta_bound_identifier",
    "ta_bound_identifier_type",
    "ta_validation_data",
    "ta_validation_last_checked",
    "ta_highest_severity",
    "ta_user_status",
    "ta_blocked_reason"
  ],
  "has_uninstall": true,
  "last_checked": "2026-02-24T23:49:17.900Z"
}