{
  "options": [
    "*_front_page_no_load",
    "*_front_page_load_exceptions",
    "*_global_unload",
    "*_bulk_unload",
    "*_post_type_load_exceptions",
    "*_front_page_data",
    "*_critical_css_config",
    "*_first_usage",
    "*_settings",
    "*_review_notice_status",
    "active_sitewide_plugins",
    "*_pro_license_key",
    "*_pro_license_status",
    "woocommerce_shop_page_id",
    "siteground_optimizer_combine_css",
    "*_extras_load_exceptions",
    "wp_rocket_settings",
    "classic-editor-replace",
    "classic-editor-allow-users",
    "sccss_settings",
    "autoptimize_css",
    "WpFastestCache",
    "litespeed-cache-conf",
    "breeze_basic_settings",
    "breeze_advanced_settings",
    "autoptimize_js",
    "*_tracking_last_send",
    "*_hide_tracking_notice",
    "*_global_data",
    "wpassetcleanup_global_data",
    "perfmatters_extras"
  ],
  "transients": [
    "*_import_done",
    "*_active_plugins_icons",
    "*_frontend_assets_manager_just_updated",
    "*_all_rules_cleared",
    "*_redirect_after_activation",
    "*_settings_updated",
    "*_reset_done",
    "*_assets_info",
    "*_last_clear_cache",
    "*_clear_assets_cache",
    "*_clear_assets_cache_via_link",
    "*_cache_just_cleared_via_link_dash_area",
    "*_preloads_just_removed",
    "*_total_unloaded_assets_all",
    "*_total_unloaded_assets_per_page"
  ],
  "cron_jobs": [
    "wpacu_daily_scheduled_events",
    "wpacu_weekly_scheduled_events"
  ],
  "custom_tables": [],
  "metadata": [
    "_wp_page_template",
    "*_load_exceptions",
    "*_no_load",
    "*_data",
    "*_page_options"
  ],
  "has_uninstall": false,
  "last_checked": "2026-02-24T22:30:50.325Z"
}