{
  "options": [
    "sktnurc_recaptcha_language",
    "sktnurc_data_theme",
    "sktnurc_data_type",
    "sktnurc_login_recaptcha",
    "sktnurc_publkey",
    "sktnurc_privtkey",
    "sktnurc_username_help",
    "sktnurc_email_help",
    "sktnurc_v2_reCaptcha_help",
    "sktnurc_usrhlp_opt",
    "sktnurc_emlhlp_opt",
    "sktnurc_rechlp_opt",
    "sktnurc_logpage_limit",
    "sktnurc_regbutton",
    "sktnurc_custom_page_list",
    "sktnurc_botscoutkey",
    "sktnurc_theme",
    "sktnurclog_db_version",
    "sktnurc_count",
    "sktnurc_botscout_active",
    "sktnurc_botscoutTestMode",
    "sktnurc_lang",
    "sktnurc_lang_set",
    "sktnurc_reCaptcha_help",
    "sktnurc_recaptcha_version",
    "sktnurc_reclocales_lang",
    "sktnurc_stopforumspam_active",
    "sktnurc_keysset"
  ],
  "transients": [],
  "cron_jobs": [],
  "custom_tables": [],
  "metadata": [],
  "has_uninstall": true,
  "last_checked": "2026-02-24T23:02:36.324Z"
}