{
  "options": [
    "simple_banner_text*",
    "hide_simple_banner*",
    "simple_banner_color*",
    "simple_banner_text_color*",
    "simple_banner_link_color*",
    "simple_banner_close_color*",
    "simple_banner_font_size*",
    "simple_banner_z_index*",
    "simple_banner_position*",
    "close_button_enabled*",
    "close_button_expiration*",
    "simple_banner_prepend_element*",
    "header_margin",
    "header_padding",
    "wp_body_open_enabled",
    "simple_banner_custom_css*",
    "simple_banner_text_custom_css*",
    "simple_banner_button_css*",
    "simple_banner_scrolling_custom_css*",
    "pro_version_enabled",
    "simple_banner_pro_license_key",
    "simple_banner_insert_inside_element*",
    "simple_banner_start_after_date*",
    "simple_banner_remove_after_date*",
    "disabled_on_posts*",
    "simple_banner_disabled_page_paths*",
    "disabled_pages_array*",
    "site_custom_css*",
    "keep_site_custom_css*",
    "site_custom_js*",
    "keep_site_custom_js*",
    "permissions_array",
    "simple_banner_debug_mode",
    "pro_version_activation_code",
    "header_margin*",
    "header_padding*",
    "wp_body_open_enabled*",
    "simple_banner_clear_cache"
  ],
  "transients": [],
  "cron_jobs": [],
  "custom_tables": [],
  "metadata": [],
  "has_uninstall": false,
  "last_checked": "2026-02-24T22:32:49.977Z"
}