{
  "options": [
    "mprm_capabilities_version",
    "mprm_install_page",
    "mprm_settings",
    "mprm_settings_general",
    "mprm_settings_gateways",
    "mprm_settings_emails",
    "mprm_settings_styles",
    "mprm_settings_taxes",
    "mprm_settings_extensions",
    "mprm_settings_licenses",
    "mprm_settings_misc",
    "mprm_last_payment_number",
    "mprm_earnings_total",
    "mprm_payment_totals_upgraded",
    "mprm_use_php_sessions",
    "mprm_tax_rates",
    "mprm_db_version",
    "*_db_version"
  ],
  "transients": [
    "mp_restaurant_add_ons_feed",
    "*_purchases",
    "mprm_earnings_total"
  ],
  "cron_jobs": [
    "wp_session_garbage_collection"
  ],
  "custom_tables": [],
  "metadata": [
    "_mprm_user_address",
    "_mprm_order_gateway",
    "_menu_item_menu_item_parent",
    "_thumbnail_id",
    "mprm_sku",
    "mprm_product_notes",
    "mp_menu_gallery",
    "_mprm_product_type",
    "mprm_price",
    "_button_behavior",
    "_mprm_menu_item_sales",
    "_mprm_price_options_mode",
    "mprm_variable_prices",
    "_disabled_checkout",
    "price",
    "_variable_pricing",
    "attributes",
    "mprm_saved_cart",
    "mprm_cart_token",
    "_mprm-pending_verification",
    "_mprm_discount_product_reqs",
    "_mprm_discount_excluded_products",
    "_mprm_discount_is_not_global",
    "_mprm_discount_type",
    "_mprm_discount_amount",
    "_mprm_discount_uses",
    "_mprm_discount_expiration",
    "_mprm_discount_start",
    "_mprm_discount_max_uses",
    "_mprm_discount_is_single_use",
    "_mprm_discount_min_price",
    "_mprm_discount_product_condition",
    "_mprm_order_user_email",
    "_mprm_menu_item_tax_exclusive",
    "_mprm_order_meta",
    "nutritional",
    "sku",
    "_mprm_order_purchase_key",
    "_mprm_default_price_id"
  ],
  "has_uninstall": false,
  "last_checked": "2026-02-24T22:43:50.916Z"
}