{
  "options": [
    "pzen_ck_api_key",
    "pzen_mc_api_key",
    "pzen_ac_api_key",
    "pzen_ac_url",
    "pzen_mc_status",
    "pzen_powered_by",
    "pzen_ga_tracking",
    "pzen_pro_edd_license",
    "mc4wp"
  ],
  "transients": [
    "pzen_mc_lists",
    "pzen_ac_lists"
  ],
  "cron_jobs": [],
  "custom_tables": [],
  "metadata": [
    "pzen_conversions",
    "pzen_active",
    "position",
    "pzen_type",
    "accent_color",
    "btn_text_color",
    "bg_color",
    "text_color",
    "pzen_title",
    "pzen_content",
    "pzen_image",
    "image_no_crop",
    "expand_btn_text",
    "name_label",
    "dont_show_name",
    "email_label",
    "opt_in_confirmation",
    "submit_text",
    "email_provider",
    "ck_id",
    "mc_list_id",
    "ac_list_id",
    "mailpoet_list_id",
    "show_on",
    "show_on_pages",
    "logged_in",
    "new_or_returning",
    "display_when",
    "page_scroll_percent",
    "scroll_delay",
    "show_settings",
    "hide_for_days",
    "pzen_devices",
    "expiration",
    "pzen_until_date",
    "pzen_redirect",
    "image_padding",
    "mc_url",
    "drip_tags",
    "mc_interests"
  ],
  "has_uninstall": false,
  "last_checked": "2026-02-24T23:17:47.571Z"
}