{
  "options": [
    "related_show",
    "related_list",
    "related_content",
    "related_content_all",
    "related_content_rss",
    "related_content_title",
    "related_content_extended",
    "related_double_plugin",
    "related_du_show",
    "related_du_list",
    "related_du_content",
    "related_du_content_all",
    "related_du_content_rss",
    "related_du_content_title",
    "related_du_content_extended"
  ],
  "transients": [],
  "cron_jobs": [],
  "custom_tables": [],
  "metadata": [
    "related_posts",
    "related_du_posts",
    "_wp_attachment_image_alt"
  ],
  "has_uninstall": true,
  "last_checked": "2026-02-24T22:48:07.261Z"
}