{
  "options": [
    "etcpf_etsy_shops",
    "etcpf_shop_name",
    "ETCPF_RESOLVED",
    "etcpf_attribute_user_map_Etsy",
    "etcpf_oauth_token",
    "etcpf_oauth_refresh_token",
    "etcpf_stage",
    "etcpf_connected_to_shop",
    "etcpf_shop_id",
    "etcpf_shop_sections_*",
    "etcpf_shop_sections_count_*",
    "etsy_current_uploading_*",
    "currently_uploading_feed_id",
    "et_cp_feed_order",
    "et_cpf_feed_order_reverse",
    "etcpf_login_url",
    "etcpf_etsyfeedActivity_*",
    "etcpf_order_limit",
    "etcf_etsy_to_woo_order_sync_left",
    "Etsy-etsy-merchant-custom-settings",
    "etcpf_licensekey_expired",
    "Etsy-etsy-merchant-settings",
    "etcpf_update_status",
    "etcpf_last_sync_date",
    "etcpf_order_limit_reached_mail_sent",
    "etcpf_api_key",
    "etcpf_secret_key",
    "etcpf_imported_to_woocommerce",
    "etsy_free_plan_product_import_limit",
    "etsy_linked_product_import_count",
    "etcpf_order_failed_limit_sent",
    "etcpf_currency_code_etsy",
    "etcpf_variation_image_linkls",
    "et_cp_feed_delay",
    "etcpf_shipping_template_id",
    "etcpf_db_upgrade_available",
    "last_api_hit_timestamp",
    "etsy_api_count",
    "etcpf_oauth_token_secret",
    "etsy_product_upload_count",
    "etsy_free_plan_product_upload_limit",
    "etcpf_processing_profile_id",
    "etcpf_return_policies",
    "etsy_variation_on_property_*",
    "etcpf_woo_etsy_connector_url",
    "etcpf_conversion_api_key",
    "etcpf_failed_order_email_sent",
    "etcpf_oauth_verfier",
    "etcpf_shop_disconnected",
    "etcpf_production_partners",
    "etcpf_etsy_shop_ids",
    "etcpf_secret",
    "woocommerce_dimension_unit",
    "woocommerce_weight_unit",
    "woocommerce_manage_stock",
    "woocommerce_hide_out_of_stock_items",
    "listing_etsy_et",
    "*-etsy-merchant-settings",
    "woocommerce_notify_no_stock_amount",
    "linked_sku_value_count",
    "etcpf_licensekey",
    "etcpf_localkey",
    "etcpf_db_upgraded",
    "etcpf_current_db_version",
    "imported_to_woocommerce",
    "not_linked_product",
    "linked_product_count",
    "etcpf_last_table_optimization",
    "etcpf_indexes_last_checked",
    "et_cp_localkey",
    "et_cp_feed_limit",
    "et_cp_feed_count",
    "etsy_order_offset",
    "etcpf_license_message",
    "active_sitewide_plugins",
    "fs_debug_mode",
    "_transient_timeout_fs_snooze_period",
    "_site_transient_timeout_fs_snooze_period",
    "fs_storage_logger",
    "fs_active_plugins"
  ],
  "transients": [
    "etcpf_coming_from_product_import",
    "etcpf_updating_counts",
    "update_plugins",
    "etcpf_notification_message",
    "etcpf_error_message",
    "fs_snooze_period",
    "_fs_api_connection_retry_counter",
    "update_themes"
  ],
  "cron_jobs": [
    "auto_etsy_order_hook",
    "auto_feed_submission_hook",
    "update_etsyfeeds_hook",
    "run_refresh_token_cron",
    "etcpf_auto_feed_submission_hook",
    "etcpf_auto_email_failed_orders",
    "etcpf_mutipl_images_upload",
    "etcpf_update_product_counts",
    "etcpf_cleanup_cache",
    "etcpf_product_update_event",
    "fs_debug_turn_off_logging_hook"
  ],
  "custom_tables": [],
  "metadata": [
    "_manage_stock",
    "_stock",
    "_imported_by_etcpf",
    "_sku",
    "custom_size",
    "material",
    "brand",
    "etcpf_etsy_receipt_id"
  ],
  "has_uninstall": false,
  "last_checked": "2026-02-24T22:50:34.767Z"
}