{
  "options": [
    "tcss_enable",
    "tcss_business_type",
    "tcss_business_name",
    "tcss_business_email",
    "tcss_business_description",
    "tcss_phone",
    "tcss_url",
    "tcss_logo",
    "tcss_image",
    "tcss_street",
    "tcss_city",
    "tcss_region",
    "tcss_postal",
    "tcss_country",
    "tcss_latitude",
    "tcss_longitude",
    "tcss_map_url",
    "tcss_opening_hours",
    "tcss_price_range",
    "tcss_currencies",
    "tcss_payments",
    "tcss_og_enable",
    "tcss_og_title",
    "tcss_og_description",
    "tcss_og_image",
    "tcss_og_image_alt",
    "tcss_og_fallback",
    "tcss_webschema_enable",
    "tcss_social_facebook",
    "tcss_social_instagram",
    "tcss_social_tiktok",
    "tcss_social_twitter",
    "tcss_social_linkedin",
    "tcss_social_pinterest",
    "tcss_social_youtube",
    "tcss_woocommerce_archive_schema",
    "tcss_single_post_schema",
    "tcss_single_product_elementor_schema",
    "tcss_fetch_priority",
    "tcss_fetch_priority_class",
    "tcss_fetch_priority_urls",
    "tcss_woocommerce_single_image_alt",
    "tcss_delete_options",
    "tcss_sitemap_enable",
    "tcss_sitemap_enable_index",
    "tcss_sitemap_control",
    "tcss_business_type_custom",
    "tcss_og_prioritized",
    "active_sitewide_plugins"
  ],
  "transients": [],
  "cron_jobs": [],
  "custom_tables": [],
  "metadata": [
    "_tcss_seo_image_id",
    "_wp_attachment_image_alt",
    "_price",
    "_stock_status"
  ],
  "has_uninstall": true,
  "last_checked": "2026-02-24T23:10:54.326Z"
}