{
  "options": [
    "theme_activation_mode",
    "accron_media_id",
    "widget_search",
    "widget_recent_entries",
    "widget_archive",
    "sidebars_widgets",
    "avril_media_id",
    "widget_archives",
    "conceptly_media_id",
    "aravalli_media_id",
    "startkit_media_id",
    "boostify_media_id",
    "item_details_page",
    "corpex_media_id",
    "widget_tag_cloud",
    "hantus_media_id",
    "eduvert_media_id",
    "evita_media_id",
    "fiona_blog_media_id",
    "gradiant_media_id",
    "medazin_media_id",
    "widget_calendar",
    "metasoft_media_id",
    "news_25_media_id",
    "widget_block",
    "custom_texo_project_id",
    "nexcraft_media_id",
    "custom_texo_faq_id",
    "renoval_media_id",
    "webique_media_id"
  ],
  "transients": [],
  "cron_jobs": [],
  "custom_tables": [],
  "metadata": [
    "_wp_page_template",
    "popular_badge",
    "packages_ribbon_text",
    "packages_price_badge",
    "packages_price",
    "packages_button_link",
    "packages_button_link_target",
    "packages_star",
    "_wp_attachment_image_alt",
    "project_button_link",
    "project_button_link_target",
    "plans_currency",
    "plans_price",
    "price_content",
    "plans_button_label",
    "price_recomended",
    "plans_button_link",
    "plans_button_link_target"
  ],
  "has_uninstall": true,
  "last_checked": "2026-02-24T22:33:43.978Z"
}